mcp_email_client/__init__.py
mcp_email_client/__main__.py
mcp_email_client/config.py
mcp_email_client/db.py
mcp_email_client/mailhandler.py
mcp_email_client/semantic.py
mcp_email_client/server.py
mcp_email_client/config/.gitignore
mcp_email_client_cybergenix-1.0.0.dist-info/METADATA
mcp_email_client_cybergenix-1.0.0.dist-info/WHEEL
mcp_email_client_cybergenix-1.0.0.dist-info/entry_points.txt
mcp_email_client_cybergenix-1.0.0.dist-info/licenses/LICENSE
mcp_email_client_cybergenix-1.0.0.dist-info/RECORD
