Metadata-Version: 2.4
Name: mcp-email-client-cybergenix
Version: 1.0.0
Summary: A Python-based MCP (Model Context Protocol) email client for managing email configurations and interactions with Claude Desktop
Project-URL: Homepage, https://github.com/gamalan/mcp-email-client
Project-URL: Repository, https://github.com/gamalan/mcp-email-client.git
Project-URL: Issues, https://github.com/gamalan/mcp-email-client/issues
Project-URL: Documentation, https://github.com/gamalan/mcp-email-client#readme
Author-email: Cybergenix <it@cybergenix.co>
Maintainer-email: Cybergenix <it@cybergenix.co>
License: MIT
License-File: LICENSE
Keywords: claude,client,desktop,email,mail,mcp
Classifier: Development Status :: 3 - Alpha
Classifier: Intended Audience :: Developers
Classifier: License :: OSI Approved :: MIT License
Classifier: Operating System :: OS Independent
Classifier: Programming Language :: Python :: 3
Classifier: Programming Language :: Python :: 3.12
Classifier: Topic :: Communications :: Email
Classifier: Topic :: Software Development :: Libraries :: Python Modules
Requires-Python: >=3.12
Requires-Dist: duckdb>=1.2.2
Requires-Dist: imapclient>=3.0.1
Requires-Dist: mcp[cli]>=1.3.0
Requires-Dist: numpy>=2.2.4
Requires-Dist: pydantic>=2.10.6
Requires-Dist: sentence-transformers>=4.1.0
